TensorflowGuanfangWendangZhongwenban/README.md
TensorflowGuanfangWendangZhongwenban/__init__.py
TensorflowGuanfangWendangZhongwenban/__main__.py
TensorflowGuanfangWendangZhongwenban/file.epub
TensorflowGuanfangWendangZhongwenban/index.html
TensorflowGuanfangWendangZhongwenban/css/__init__.py
TensorflowGuanfangWendangZhongwenban/css/annotations.css
TensorflowGuanfangWendangZhongwenban/css/main.css
TensorflowGuanfangWendangZhongwenban/css/normalize.css
TensorflowGuanfangWendangZhongwenban/css/popup.css
TensorflowGuanfangWendangZhongwenban/font/__init__.py
TensorflowGuanfangWendangZhongwenban/font/fontello.eot
TensorflowGuanfangWendangZhongwenban/font/fontello.svg
TensorflowGuanfangWendangZhongwenban/font/fontello.ttf
TensorflowGuanfangWendangZhongwenban/font/fontello.woff
TensorflowGuanfangWendangZhongwenban/img/__init__.py
TensorflowGuanfangWendangZhongwenban/img/annotator-glyph-sprite.png
TensorflowGuanfangWendangZhongwenban/img/annotator-icon-sprite.png
TensorflowGuanfangWendangZhongwenban/img/apple-touch-icon.png
TensorflowGuanfangWendangZhongwenban/img/cancelfullscreen.png
TensorflowGuanfangWendangZhongwenban/img/close.png
TensorflowGuanfangWendangZhongwenban/img/fullscreen.png
TensorflowGuanfangWendangZhongwenban/img/loader.gif
TensorflowGuanfangWendangZhongwenban/img/menu-icon.png
TensorflowGuanfangWendangZhongwenban/img/save.png
TensorflowGuanfangWendangZhongwenban/img/saved.png
TensorflowGuanfangWendangZhongwenban/img/settings-s.png
TensorflowGuanfangWendangZhongwenban/img/settings.png
TensorflowGuanfangWendangZhongwenban/img/star.png
TensorflowGuanfangWendangZhongwenban/js/__init__.py
TensorflowGuanfangWendangZhongwenban/js/epub.js
TensorflowGuanfangWendangZhongwenban/js/epub.min.js
TensorflowGuanfangWendangZhongwenban/js/epub.min.map
TensorflowGuanfangWendangZhongwenban/js/hooks.min.js
TensorflowGuanfangWendangZhongwenban/js/hooks.min.map
TensorflowGuanfangWendangZhongwenban/js/reader.js
TensorflowGuanfangWendangZhongwenban/js/reader.js.map
tensorflow_guanfang_wendang_zhongwenban-2024.3.2.0.dist-info/METADATA
tensorflow_guanfang_wendang_zhongwenban-2024.3.2.0.dist-info/WHEEL
tensorflow_guanfang_wendang_zhongwenban-2024.3.2.0.dist-info/entry_points.txt
tensorflow_guanfang_wendang_zhongwenban-2024.3.2.0.dist-info/top_level.txt
tensorflow_guanfang_wendang_zhongwenban-2024.3.2.0.dist-info/RECORD
